yourstyle/__init__.py
yourstyle/your_custom_style.py
yourstyle-0.2.dist-info/METADATA
yourstyle-0.2.dist-info/WHEEL
yourstyle-0.2.dist-info/entry_points.txt
yourstyle-0.2.dist-info/top_level.txt
yourstyle-0.2.dist-info/RECORD
