Metadata-Version: 2.1
Name: yourstyle
Version: 0.2
Requires-Dist: pygments (>=2.0)
